noaithx/__init__.py
noaithx/__main__.py
noaithx/commentbuilder.py
noaithx/commenter.py
noaithx/commentgen.py
noaithx/content.py
noaithx/main.py
noaithx/content/closer.txt
noaithx/content/maths.json
noaithx/content/opener.txt
noaithx/content/silly.json
noaithx-0.0.2.dist-info/METADATA
noaithx-0.0.2.dist-info/WHEEL
noaithx-0.0.2.dist-info/entry_points.txt
noaithx-0.0.2.dist-info/top_level.txt
noaithx-0.0.2.dist-info/RECORD
