Metadata-Version: 2.4
Name: noaithx
Version: 0.0.2
Summary: Silly little utility for outputting anti-AI comments to make those forced AI code reviews more fun
Author-email: Ryan Harvey <rkharvey@mekapaedia.com>
License-Expression: MIT
Project-URL: Homepage, https://github.com/Mekapaedia/noaithx
Project-URL: Repository, https://github.com/Mekapaedia/noaithx.git
Keywords: toy,comments
Classifier: Development Status :: 3 - Alpha
Classifier: Programming Language :: Python
Requires-Python: >=3.0
